heare/config/__init__.py
heare_config-1.0.7.dist-info/LICENSE
heare_config-1.0.7.dist-info/METADATA
heare_config-1.0.7.dist-info/WHEEL
heare_config-1.0.7.dist-info/top_level.txt
heare_config-1.0.7.dist-info/RECORD
