Metadata-Version: 2.1
Name: heare-config
Version: 1.0.7
Summary: Heare.io Configuration Utilities
Home-page: https://github.com/heare-io/heare-config
Author: Sean Fitzgerald
Author-email: seanfitz@heare.io
License-File: LICENSE
